pytest_browserstack/__init__.py
pytest_browserstack/constants.py
pytest_browserstack/driver.py
pytest_browserstack/fixtures.py
pytest_browserstack/helpers.py
pytest_browserstack/screenshots.py
pytest_browserstack/services.py
pytest_browserstack-0.1.dist-info/DESCRIPTION.rst
pytest_browserstack-0.1.dist-info/METADATA
pytest_browserstack-0.1.dist-info/RECORD
pytest_browserstack-0.1.dist-info/WHEEL
pytest_browserstack-0.1.dist-info/entry_points.txt
pytest_browserstack-0.1.dist-info/metadata.json
pytest_browserstack-0.1.dist-info/top_level.txt
